usit/__init__.py
usit/version.txt
usit/core/__init__.py
usit/core/_config.py
usit/core/_drivers.py
usit/core/_web.py
usit/core/devices/__init__.py
usit/core/devices/_elements.py
usit/core/devices/_index.py
usit/core/devices/_loader.py
usit/core/devices/_manager.py
usit/core/files/__init__.py
usit/core/files/devices_index.ini
usit/core/files/launcher.cmd
usit/core/files/launcher.py
usit/core/files/usit.py
usit/core/gui/__init__.py
usit/core/gui/controlcenter/__init__.py
usit/core/gui/controlcenter/interface.ui
usit/core/gui/controlcenter/main.py
usit/core/gui/controlcenter/thread.py
usit/core/gui/controlcenter/treewidgets.py
usit/core/gui/monitoring/__init__.py
usit/core/gui/monitoring/data.py
usit/core/gui/monitoring/figure.py
usit/core/gui/monitoring/interface.ui
usit/core/gui/monitoring/main.py
usit/core/gui/monitoring/monitor.py
usit/core/gui/scanning/__init__.py
usit/core/gui/scanning/config.py
usit/core/gui/scanning/data.py
usit/core/gui/scanning/figure.py
usit/core/gui/scanning/interface.ui
usit/core/gui/scanning/main.py
usit/core/gui/scanning/parameter.py
usit/core/gui/scanning/recipe.py
usit/core/gui/scanning/scan.py
usit/core/gui/scanning/scanrange.py
usit/core/recorder_old/__init__.py
usit/core/recorder_old/recorder.py
usit/drivers/__init__.py
usit/drivers/agilent_33220a/__init__.py
usit/drivers/agilent_33220a/agilent_33220a.py
usit/drivers/agilent_81150A/__init__.py
usit/drivers/agilent_81150A/agilent_81150A.py
usit/drivers/agilent_DSA91304A/__init__.py
usit/drivers/agilent_DSA91304A/agilent_DSA91304A.py
usit/drivers/agilent_DSA91304A/scope_DSA91304A.py
usit/drivers/agilent_DSA91304A/yt_DSA91304A.py
usit/drivers/agilent_DSO54853A/__init__.py
usit/drivers/agilent_DSO54853A/agilent_DSO54853A.py
usit/drivers/agilent_DSO81204B/__init__.py
usit/drivers/agilent_DSO81204B/agilent_DSO81204B.py
usit/drivers/agilent_DSO81204B/scope_DSO81204B.py
usit/drivers/agilent_E8244A/__init__.py
usit/drivers/agilent_E8244A/agilent_E8244A.py
usit-1.0.4.dist-info/LICENSE
usit-1.0.4.dist-info/METADATA
usit-1.0.4.dist-info/WHEEL
usit-1.0.4.dist-info/entry_points.txt
usit-1.0.4.dist-info/top_level.txt
usit-1.0.4.dist-info/RECORD
