Metadata-Version: 2.1
Name: usit
Version: 1.0.4
Summary: Universal Scanning Interface : python package for scientific experiments automation
Home-page: https://github.com/qcha41/usit
Author: Quentin Chateiller
Author-email: q.chateiller@gmail.com
License: UNKNOWN
Keywords: Universal,Scanning,Interface,automation,scientific,laboratory,experiments,measures
Platform: UNKNOWN
Classifier: Programming Language :: Python :: 3
Classifier: Operating System :: OS Independent
